{"id":"e1e8e480","img":"/imgs/e1e8e480.jpeg","description":"🎉 🎉 🎉 🎉麵屋雞金 購雞白創意料理大賽進行中🎉 🎉 🎉 🎉\n最近三級警戒，只能待在家，但是湯麵類型的外帶味道又會打折，喜歡吃拉麵的朋友們應該非常苦惱吧?\n我們全都幫你準備好了!!簡單6分鐘味道跟店內現煮的一模一樣，再加點不一樣材料，還可以簡單做出很豐富的變化。疫情期間請盡量不要外出啦!!一起努力降低疫情影響吧!!\n所以小編決定舉辦🥳 🥳麵屋雞金 購雞白創意料理大賽🥳 🥳\n\n只要購買麵屋雞金 雞白湯拉麵冷凍包並在IG上秀出你最有創意的吃法，就有機會得到5盒麵屋雞金冷凍包!名額總計10位，獲選者看你要5盒留著自己吃還是全部分送親朋好友，我們通通幫你寄，運費小編來付🚚 🚚 🚚\n\n #麵屋雞金購雞白創意料理  #麵屋雞金  #雞白湯  #雞白湯拉麵  #9折  #拉麵冷凍包\n\n活動詳細辦法如下：\n1.\t活動時間：5/24~6/6(以發文時間為準)\n2.\t即日起，麵屋雞金拉麵冷凍包全面九折(原價540元，特價485元)，優惠到6/6截止，麵屋雞金光華店及五之神製作所優惠同步進行(現場買免運費)。\n3.\t追蹤麵屋雞金IG\n4.\t活動期間於IG發文貼出你使用麵屋雞金拉麵冷凍包做出的最有創意料理照片或影片，作品拍照的時候必須將購買的雞金冷凍包外包裝盒一起入鏡(作品不限料理型式，你要做成雞白湯燉飯都行!)\n5.\t文章內簡單描述作法(教教廚藝苦手的小編媽媽)\n6.\t@兩位好友和@torikintw，以及在文章最後打上  #麵屋雞金購雞白創意料理\n7.\t小編會依照自己喜好選出10位優秀創意者，各送5盒雞白湯拉麵冷凍包，送人或自用都可以，我們通通幫你寄。運費小編付!!\n8.\t獲選名單會在6/8前公布在麵屋雞金及五之神製作所的FB粉絲團及IG，請獲選者在6/13前於IG私訊小編，告知你要寄送的地址及盒數(總共5盒)，例如：小編爸家1盒，小編家1盒，小編喜歡的三個女生各1盒，總計5盒。\n9.\t主辦單位保有本活動最終解釋權，若因不可抗力因素導致活動取消或延期舉辦，將會公告於雞金FB及IG，恕不另行通知。\n\n #麵屋雞金購雞白創意料理  #麵屋雞金  #雞白湯  #雞白湯拉麵  #9折  #拉麵冷凍包販售中","likes":"24","comments":"0","time":"2 years ago","crawlerTime":"2023-01-28T14:52:44.765Z","isLimitedRamen":false,"limitRamenName":null}